nombot/__init__.py
nombot/algorithms/__init__.py
nombot/api/__init__.py
nombot/api/coinigy_request.py
nombot/api/coinigy_response.py
nombot/api/request.py
nombot/api/response.py
nombot/api/services/__init__.py
nombot/api/services/ccxt.py
nombot/api/services/coinigy.py
nombot/app/__init__.py
nombot/app/builder.py
nombot/app/config.py
nombot/generics/__init__.py
nombot/generics/coinigy.py
nombot/generics/config.py
nombot/generics/context.py
nombot/generics/exchange.py
nombot/generics/request.py
nombot/generics/response.py
nombot/strategies/__init__.py
nombot/strategies/basic_trading.py
nombot/strategies/mm.py
nombot/strategies/print.py
nombot/strategies/middleware/__init__.py
nombot/strategies/middleware/coinigy.py
nombot/strategies/middleware/trading.py
nombot-2.2.9.dist-info/METADATA
nombot-2.2.9.dist-info/RECORD
nombot-2.2.9.dist-info/WHEEL
nombot-2.2.9.dist-info/entry_points.txt
nombot-2.2.9.dist-info/top_level.txt
