Metadata-Version: 2.1
Name: nombot
Version: 2.2.9
Summary: A cryptocurrency trading bot
Home-page: https://github.com/karma0/nombot
Author: Bobby
Author-email: karma0@gmail.com
License: GNU General Public License v3
Keywords: nombot cryptocurrency bot
Platform: UNKNOWN
Classifier: Development Status :: 2 - Pre-Alpha
Classifier: Intended Audience :: Developers
Classifier: License :: OSI Approved :: GNU General Public License v3 (GPLv3)
Classifier: Natural Language :: English
Classifier: Programming Language :: Python :: 3.6
Requires-Dist: marshmallow
Requires-Dist: requests
Requires-Dist: urllib3
Requires-Dist: bors
Requires-Dist: click
Requires-Dist: ccxt
